{
  "dependencies": {
    "appInsights1": {
      "resourceId": "/subscriptions/[parameters('subscriptionId')]/resourceGroups/[parameters('resourceGroupName')]/providers/microsoft.insights/components/az304demo",
      "type": "appInsights.azure",
      "connectionId": "APPINSIGHTS_CONNECTIONSTRING",
      "secretStore": "AzureAppSettings"
    },
    "secrets1": {
      "resourceId": "/subscriptions/[parameters('subscriptionId')]/resourceGroups/[parameters('resourceGroupName')]/providers/Microsoft.KeyVault/vaults/az304demoServervault",
      "type": "secrets.keyVault",
      "connectionId": "VaultUri",
      "secretStore": "AzureAppSettings"
    }
  }
}